Metadata-Version: 1.1
Name: tnumbers
Version: 0.0.1
Summary: This package gives a list of evens,odds and prime numbers between two numbers(both inclusive)
Home-page: https://github.com/Trimuchinni/tnumbers
Author: Trimurthulu Chinni
Author-email: trimuchinni23@gmail.com
License: MIT
Keywords: evens,even,odds,odd,numbers,number,primes,prime,between,evens between,odds between,primes between
Platform: UNKNOWN
Classifier: Development Status :: 5 - Production/Stable
Classifier: Intended Audience :: Education
Classifier: Intended Audience :: Developers
Classifier: Operating System :: Microsoft :: Windows :: Windows 10
Classifier: License :: OSI Approved :: MIT License
Classifier: Programming Language :: Python :: 3
